odoo/addons/l10n_fr_ecotaxe/README.rst
odoo/addons/l10n_fr_ecotaxe/__init__.py
odoo/addons/l10n_fr_ecotaxe/__manifest__.py
odoo/addons/l10n_fr_ecotaxe/data/decimal_precision.xml
odoo/addons/l10n_fr_ecotaxe/i18n/am.po
odoo/addons/l10n_fr_ecotaxe/i18n/ar.po
odoo/addons/l10n_fr_ecotaxe/i18n/bg.po
odoo/addons/l10n_fr_ecotaxe/i18n/bs.po
odoo/addons/l10n_fr_ecotaxe/i18n/ca.po
odoo/addons/l10n_fr_ecotaxe/i18n/ca_ES.po
odoo/addons/l10n_fr_ecotaxe/i18n/cs.po
odoo/addons/l10n_fr_ecotaxe/i18n/cs_CZ.po
odoo/addons/l10n_fr_ecotaxe/i18n/da.po
odoo/addons/l10n_fr_ecotaxe/i18n/de.po
odoo/addons/l10n_fr_ecotaxe/i18n/el_GR.po
odoo/addons/l10n_fr_ecotaxe/i18n/en_GB.po
odoo/addons/l10n_fr_ecotaxe/i18n/es.po
odoo/addons/l10n_fr_ecotaxe/i18n/es_AR.po
odoo/addons/l10n_fr_ecotaxe/i18n/es_CL.po
odoo/addons/l10n_fr_ecotaxe/i18n/es_CO.po
odoo/addons/l10n_fr_ecotaxe/i18n/es_CR.po
odoo/addons/l10n_fr_ecotaxe/i18n/es_DO.po
odoo/addons/l10n_fr_ecotaxe/i18n/es_EC.po
odoo/addons/l10n_fr_ecotaxe/i18n/es_ES.po
odoo/addons/l10n_fr_ecotaxe/i18n/es_MX.po
odoo/addons/l10n_fr_ecotaxe/i18n/es_PE.po
odoo/addons/l10n_fr_ecotaxe/i18n/es_PY.po
odoo/addons/l10n_fr_ecotaxe/i18n/es_VE.po
odoo/addons/l10n_fr_ecotaxe/i18n/et.po
odoo/addons/l10n_fr_ecotaxe/i18n/eu.po
odoo/addons/l10n_fr_ecotaxe/i18n/fa.po
odoo/addons/l10n_fr_ecotaxe/i18n/fi.po
odoo/addons/l10n_fr_ecotaxe/i18n/fr.po
odoo/addons/l10n_fr_ecotaxe/i18n/fr_CA.po
odoo/addons/l10n_fr_ecotaxe/i18n/fr_CH.po
odoo/addons/l10n_fr_ecotaxe/i18n/fr_FR.po
odoo/addons/l10n_fr_ecotaxe/i18n/gl.po
odoo/addons/l10n_fr_ecotaxe/i18n/gl_ES.po
odoo/addons/l10n_fr_ecotaxe/i18n/he.po
odoo/addons/l10n_fr_ecotaxe/i18n/hr.po
odoo/addons/l10n_fr_ecotaxe/i18n/hr_HR.po
odoo/addons/l10n_fr_ecotaxe/i18n/hu.po
odoo/addons/l10n_fr_ecotaxe/i18n/id.po
odoo/addons/l10n_fr_ecotaxe/i18n/it.po
odoo/addons/l10n_fr_ecotaxe/i18n/ja.po
odoo/addons/l10n_fr_ecotaxe/i18n/ko.po
odoo/addons/l10n_fr_ecotaxe/i18n/l10n_fr_ecotaxe.pot
odoo/addons/l10n_fr_ecotaxe/i18n/lt.po
odoo_addon_l10n_fr_ecotaxe-17.0.1.0.0.3.dist-info/METADATA
odoo_addon_l10n_fr_ecotaxe-17.0.1.0.0.3.dist-info/WHEEL
odoo_addon_l10n_fr_ecotaxe-17.0.1.0.0.3.dist-info/top_level.txt
odoo_addon_l10n_fr_ecotaxe-17.0.1.0.0.3.dist-info/RECORD
